{
	"name": "pl_emp_param",
	"properties": {
		"activities": [
			{
				"name": "Copy data1",
				"type": "Copy",
				"dependsOn": [],
				"policy": {
					"timeout": "0.12:00:00",
					"retry": 0,
					"retryIntervalInSeconds": 30,
					"secureOutput": false,
					"secureInput": false
				},
				"userProperties": [],
				"typeProperties": {
					"source": {
						"type": "DelimitedTextSource",
						"storeSettings": {
							"type": "AzureBlobStorageReadSettings",
							"recursive": true,
							"enablePartitionDiscovery": false
						},
						"formatSettings": {
							"type": "DelimitedTextReadSettings"
						}
					},
					"sink": {
						"type": "DelimitedTextSink",
						"storeSettings": {
							"type": "AzureBlobStorageWriteSettings"
						},
						"formatSettings": {
							"type": "DelimitedTextWriteSettings",
							"quoteAllText": true,
							"fileExtension": ".txt"
						}
					},
					"enableStaging": false,
					"translator": {
						"type": "TabularTranslator",
						"typeConversion": true,
						"typeConversionSettings": {
							"allowDataTruncation": true,
							"treatBooleanAsNumber": false
						}
					}
				},
				"inputs": [
					{
						"referenceName": "blob_csv_param",
						"type": "DatasetReference",
						"parameters": {
							"container": "input",
							"filename": "emp_sample.csv"
						}
					}
				],
				"outputs": [
					{
						"referenceName": "blob_csv_output_param",
						"type": "DatasetReference",
						"parameters": {
							"container_output": {
								"value": "@pipeline().parameters.container_output",
								"type": "Expression"
							},
							"filename_output": {
								"value": "@pipeline().parameters.Filename_output",
								"type": "Expression"
							}
						}
					}
				]
			}
		],
		"parameters": {
			"container_input": {
				"type": "string"
			},
			"Filename_input": {
				"type": "string"
			},
			"container_output": {
				"type": "string"
			},
			"Filename_output": {
				"type": "string"
			}
		},
		"annotations": []
	}
}